rafay/__init__.py
rafay/rafay.py
rafay-1.0.5.dist-info/METADATA
rafay-1.0.5.dist-info/WHEEL
rafay-1.0.5.dist-info/top_level.txt
rafay-1.0.5.dist-info/RECORD
