Metadata-Version: 2.4
Name: rafay
Version: 1.0.5
Summary: simple package
Author: Muhammad Rafay Shaikh
Author-email: datascience.youexcel@gmail.com
Requires-Python: >=3.6
Dynamic: author
Dynamic: author-email
Dynamic: requires-python
Dynamic: summary
